{
  "date": "2026-07-01",
  "mentions": {
    "colorless_blind": 2,
    "colorless_discovery": 1,
    "colorless_finesse": 6,
    "colorless_flash_of_steel": 1,
    "colorless_metamorphosis": 2,
    "colorless_mind_blast": 1,
    "curse_injury": 1,
    "curse_parasite": 1,
    "defect_claw": 8,
    "defect_consume": 1,
    "defect_creative_ai": 1,
    "defect_echo_form": 1,
    "defect_equilibrium": 1,
    "defect_glacier": 1,
    "defect_go_for_the_eyes": 1,
    "defect_hologram": 1,
    "defect_loop": 2,
    "defect_overclock": 3,
    "defect_storm": 1,
    "defect_tempest": 1,
    "defect_turbo": 6,
    "defect_white_noise": 1,
    "ironclad_anger": 3,
    "ironclad_armaments": 1,
    "ironclad_barricade": 4,
    "ironclad_bloodletting": 2,
    "ironclad_body_slam": 2,
    "ironclad_corruption": 2,
    "ironclad_dark_embrace": 1,
    "ironclad_flex": 4,
    "ironclad_headbutt": 1,
    "ironclad_heavy_blade": 1,
    "ironclad_immolate": 1,
    "ironclad_inflame": 1,
    "ironclad_iron_wave": 1,
    "ironclad_limit_break": 1,
    "ironclad_metallicize": 3,
    "ironclad_rage": 1,
    "ironclad_rampage": 1,
    "ironclad_thunderclap": 2,
    "ironclad_twin_strike": 1,
    "necrobinder_corpse_explosion": 3,
    "necrobinder_sacrifice": 2,
    "necrobinder_wither": 2,
    "regent_snakebite": 1,
    "regent_squeeze": 3,
    "silent_adrenaline": 3,
    "silent_after_image": 2,
    "silent_blade_dance": 2,
    "silent_calculated_gamble": 1,
    "silent_corpse_explosion": 3,
    "silent_escape_plan": 1,
    "silent_noxious_fumes": 1,
    "silent_prepared": 5,
    "silent_setup": 3,
    "silent_storm_of_steel": 1,
    "silent_wraith_form": 1
  },
  "total_comments": 400
}