{
  "date": "2026-03-09",
  "mentions": {
    "colorless_apotheosis": 3,
    "colorless_blind": 5,
    "colorless_dark_shackles": 1,
    "colorless_enlightenment": 1,
    "colorless_finesse": 1,
    "colorless_flash_of_steel": 3,
    "colorless_madness": 1,
    "colorless_master_of_strategy": 1,
    "colorless_mayhem": 1,
    "colorless_metamorphosis": 1,
    "colorless_panic_button": 13,
    "colorless_the_bomb": 1,
    "curse_clumsy": 1,
    "curse_decay": 1,
    "curse_doubt": 1,
    "curse_normality": 1,
    "curse_pain": 4,
    "curse_parasite": 1,
    "curse_regret": 1,
    "curse_shame": 4,
    "defect_ball_lightning": 1,
    "defect_biased_cognition": 1,
    "defect_blizzard": 5,
    "defect_buffer": 1,
    "defect_capacitor": 2,
    "defect_chaos": 3,
    "defect_chill": 1,
    "defect_claw": 7,
    "defect_consume": 4,
    "defect_creative_ai": 1,
    "defect_darkness": 1,
    "defect_double_energy": 1,
    "defect_echo_form": 6,
    "defect_electrodynamics": 2,
    "defect_genetic_algorithm": 1,
    "defect_hologram": 1,
    "defect_loop": 8,
    "defect_melter": 1,
    "defect_overclock": 2,
    "defect_rainbow": 3,
    "defect_reboot": 2,
    "defect_scrape": 1,
    "defect_stack": 18,
    "defect_storm": 1,
    "ironclad_armaments": 1,
    "ironclad_barricade": 10,
    "ironclad_bash": 3,
    "ironclad_battle_trance": 3,
    "ironclad_berserk": 2,
    "ironclad_blood_for_blood": 1,
    "ironclad_bloodletting": 2,
    "ironclad_bludgeon": 2,
    "ironclad_body_slam": 3,
    "ironclad_burning_pact": 1,
    "ironclad_corruption": 2,
    "ironclad_dark_embrace": 2,
    "ironclad_demon_form": 2,
    "ironclad_entrench": 1,
    "ironclad_feed": 2,
    "ironclad_feel_no_pain": 2,
    "ironclad_fiend_fire": 2,
    "ironclad_flame_barrier": 1,
    "ironclad_havoc": 2,
    "ironclad_headbutt": 1,
    "ironclad_immolate": 2,
    "ironclad_offering": 1,
    "ironclad_perfected_strike": 4,
    "ironclad_pommel_strike": 4,
    "ironclad_rage": 7,
    "ironclad_rampage": 1,
    "ironclad_reaper": 2,
    "ironclad_rupture": 3,
    "ironclad_searing_blow": 1,
    "ironclad_true_grit": 1,
    "ironclad_whirlwind": 3,
    "necrobinder_sacrifice": 3,
    "regent_snakebite": 7,
    "regent_squeeze": 1,
    "silent_acrobatics": 12,
    "silent_adrenaline": 5,
    "silent_backflip": 5,
    "silent_backstab": 2,
    "silent_bane": 2,
    "silent_blade_dance": 15,
    "silent_bouncing_flask": 6,
    "silent_bullet_time": 2,
    "silent_burst": 16,
    "silent_calculated_gamble": 9,
    "silent_catalyst": 16,
    "silent_cloak_and_dagger": 2,
    "silent_dagger_spray": 1,
    "silent_dash": 1,
    "silent_deadly_poison": 7,
    "silent_dodge_and_roll": 1,
    "silent_envenom": 12,
    "silent_finisher": 11,
    "silent_footwork": 2,
    "silent_grand_finale": 2,
    "silent_noxious_fumes": 6,
    "silent_outmaneuver": 2,
    "silent_phantasmal_killer": 2,
    "silent_prepared": 14,
    "silent_reflex": 2,
    "silent_setup": 11,
    "silent_skewer": 2,
    "silent_storm_of_steel": 1,
    "silent_sucker_punch": 1,
    "silent_tactician": 3,
    "silent_terror": 3,
    "silent_tools_of_the_trade": 1,
    "silent_unload": 1,
    "silent_well_laid_plans": 2,
    "silent_wraith_form": 2
  },
  "total_comments": 2000
}